messagequeue/__init__.py
messagequeue/message_queue.py
smartez_mq-0.0.8.dist-info/LICENSE
smartez_mq-0.0.8.dist-info/METADATA
smartez_mq-0.0.8.dist-info/WHEEL
smartez_mq-0.0.8.dist-info/top_level.txt
smartez_mq-0.0.8.dist-info/RECORD
