Metadata-Version: 2.1
Name: smartez-mq
Version: 0.0.8
Summary: Simple message queue package used for smartez
Home-page: https://github.com/BispensGipsGebis/smartez-mq
Author: Rune Lykke-Kjeldsen
Author-email: rune@lykke-kjeldsen.dk
Project-URL: Bug Tracker, https://github.com/BispensGipsGebis/smartez-mq/issues
Classifier: Programming Language :: Python :: 3
Classifier: License :: OSI Approved :: MIT License
Classifier: Operating System :: OS Independent
Requires-Python: >=3.7
License-File: LICENSE
Requires-Dist: python-dotenv
Requires-Dist: smartez-logger
